ZhihuWendaYuangongLizhiBaofuGongsiDaozhiGongsiZhongdasunshiKuadiaoDaobiShiShenmeTiyanFix1/README.md
ZhihuWendaYuangongLizhiBaofuGongsiDaozhiGongsiZhongdasunshiKuadiaoDaobiShiShenmeTiyanFix1/__init__.py
ZhihuWendaYuangongLizhiBaofuGongsiDaozhiGongsiZhongdasunshiKuadiaoDaobiShiShenmeTiyanFix1/__main__.py
ZhihuWendaYuangongLizhiBaofuGongsiDaozhiGongsiZhongdasunshiKuadiaoDaobiShiShenmeTiyanFix1/file.epub
ZhihuWendaYuangongLizhiBaofuGongsiDaozhiGongsiZhongdasunshiKuadiaoDaobiShiShenmeTiyanFix1/index.html
ZhihuWendaYuangongLizhiBaofuGongsiDaozhiGongsiZhongdasunshiKuadiaoDaobiShiShenmeTiyanFix1/css/__init__.py
ZhihuWendaYuangongLizhiBaofuGongsiDaozhiGongsiZhongdasunshiKuadiaoDaobiShiShenmeTiyanFix1/css/annotations.css
ZhihuWendaYuangongLizhiBaofuGongsiDaozhiGongsiZhongdasunshiKuadiaoDaobiShiShenmeTiyanFix1/css/main.css
ZhihuWendaYuangongLizhiBaofuGongsiDaozhiGongsiZhongdasunshiKuadiaoDaobiShiShenmeTiyanFix1/css/normalize.css
ZhihuWendaYuangongLizhiBaofuGongsiDaozhiGongsiZhongdasunshiKuadiaoDaobiShiShenmeTiyanFix1/css/popup.css
ZhihuWendaYuangongLizhiBaofuGongsiDaozhiGongsiZhongdasunshiKuadiaoDaobiShiShenmeTiyanFix1/font/__init__.py
ZhihuWendaYuangongLizhiBaofuGongsiDaozhiGongsiZhongdasunshiKuadiaoDaobiShiShenmeTiyanFix1/font/fontello.eot
ZhihuWendaYuangongLizhiBaofuGongsiDaozhiGongsiZhongdasunshiKuadiaoDaobiShiShenmeTiyanFix1/font/fontello.svg
ZhihuWendaYuangongLizhiBaofuGongsiDaozhiGongsiZhongdasunshiKuadiaoDaobiShiShenmeTiyanFix1/font/fontello.ttf
ZhihuWendaYuangongLizhiBaofuGongsiDaozhiGongsiZhongdasunshiKuadiaoDaobiShiShenmeTiyanFix1/font/fontello.woff
ZhihuWendaYuangongLizhiBaofuGongsiDaozhiGongsiZhongdasunshiKuadiaoDaobiShiShenmeTiyanFix1/img/__init__.py
ZhihuWendaYuangongLizhiBaofuGongsiDaozhiGongsiZhongdasunshiKuadiaoDaobiShiShenmeTiyanFix1/img/annotator-glyph-sprite.png
ZhihuWendaYuangongLizhiBaofuGongsiDaozhiGongsiZhongdasunshiKuadiaoDaobiShiShenmeTiyanFix1/img/annotator-icon-sprite.png
zhihu_wenda_yuangong_lizhi_baofu_gongsi_daozhi_gongsi_zhongdasunshi_kuadiao_daobi_shi_shenme_tiyan_fix1-2025.3.24.1.dist-info/METADATA
zhihu_wenda_yuangong_lizhi_baofu_gongsi_daozhi_gongsi_zhongdasunshi_kuadiao_daobi_shi_shenme_tiyan_fix1-2025.3.24.1.dist-info/WHEEL
zhihu_wenda_yuangong_lizhi_baofu_gongsi_daozhi_gongsi_zhongdasunshi_kuadiao_daobi_shi_shenme_tiyan_fix1-2025.3.24.1.dist-info/entry_points.txt
zhihu_wenda_yuangong_lizhi_baofu_gongsi_daozhi_gongsi_zhongdasunshi_kuadiao_daobi_shi_shenme_tiyan_fix1-2025.3.24.1.dist-info/top_level.txt
zhihu_wenda_yuangong_lizhi_baofu_gongsi_daozhi_gongsi_zhongdasunshi_kuadiao_daobi_shi_shenme_tiyan_fix1-2025.3.24.1.dist-info/RECORD
